{
  "assessment_id": "99753e52-a2ab-489e-94cd-c68d23d566b3",
  "candidate_name": "Luis Williams",
  "candidate_email": "venkat.posanipalle3103@gmail.com",
  "test_type": "data_science",
  "link": "https://www.hackerrank.com/test/data-science-test?candidate=99753e52-a2ab-489e-94cd-c68d23d566b3",
  "created_at": "2025-05-25T01:20:20.930118",
  "deadline": "2025-06-01T01:20:20.930110",
  "duration": "90 minutes",
  "status": "sent",
  "topics": [
    "NumPy",
    "Pandas",
    "Statistics",
    "Machine Learning Basics"
  ]
}